llama2_py.py
llama2_py-0.0.6.dist-info/LICENSE
llama2_py-0.0.6.dist-info/METADATA
llama2_py-0.0.6.dist-info/WHEEL
llama2_py-0.0.6.dist-info/top_level.txt
llama2_py-0.0.6.dist-info/RECORD
