Metadata-Version: 2.1
Name: llama2-py
Version: 0.0.6
Summary: Inference Llama 2 in one file of pure Python
Author: Aydyn Tairov
Classifier: Programming Language :: Python :: 3
Classifier: License :: OSI Approved :: MIT License
Classifier: Operating System :: OS Independent
Requires-Python: >=3.6
License-File: LICENSE
